form_tools/__init__.py
form_tools/command_line.py
form_tools/form_meta/__init__.py
form_tools/form_meta/bounding_box.py
form_tools/form_meta/extractors/__init__.py
form_tools/form_meta/extractors/pdf_form_extractor.py
form_tools/form_meta/form_field.py
form_tools/form_meta/form_meta.py
form_tools/form_operators/__init__.py
form_tools/form_operators/bounding_box_operator.py
form_tools/form_operators/form_operator.py
form_tools/form_operators/form_page_operator.py
form_tools/form_operators/ocr_engines/base.py
form_tools/form_operators/ocr_engines/tesseract.py
form_tools/form_operators/operator_configs.py
form_tools/form_operators/preprocessors.py
form_tools/utils/__init__.py
form_tools/utils/constants.py
form_tools/utils/converters.py
form_tools/utils/image_reader.py
form_tools-0.2.0.dist-info/LICENSE.md
form_tools-0.2.0.dist-info/METADATA
form_tools-0.2.0.dist-info/WHEEL
form_tools-0.2.0.dist-info/entry_points.txt
form_tools-0.2.0.dist-info/RECORD
