Metadata-Version: 2.1
Name: form-tools
Version: 0.2.0
Summary: 
Author: gwionap
Author-email: gwion.aprhobat@justice.gov.uk
Requires-Python: >=3.9,<3.13
Classifier: Programming Language :: Python :: 3
Classifier: Programming Language :: Python :: 3.9
Classifier: Programming Language :: Python :: 3.10
Classifier: Programming Language :: Python :: 3.11
Classifier: Programming Language :: Python :: 3.12
Requires-Dist: Pillow (>=9.2,<11.0)
Requires-Dist: arrow-pd-parser (>=v1.3.3,<2.0.0)
Requires-Dist: awswrangler (>=2.17.0)
Requires-Dist: charset-normalizer (>=2.1.0,<3.0.0)
Requires-Dist: dataengineeringutils3 (>=1.4.1,<2.0.0)
Requires-Dist: jsonschema (>=4.7.2,<5.0.0)
Requires-Dist: mojap-metadata (>=1.10.2,<2.0.0)
Requires-Dist: opencv-python (>=4.6.0.66,<5.0.0.0)
Requires-Dist: pdf2image (>=1.16.0,<2.0.0)
Requires-Dist: pdfminer-six (>=20220524,<20220525)
Requires-Dist: pydantic (>=1.10.2,<2.0.0)
Requires-Dist: pytesseract (>=0.3.9,<0.4.0)
Requires-Dist: tesserocr (>=v2.5.2,<=2.7.0)
Requires-Dist: virtualenv (>=20.24.6)
